psod/__init__.py
psod/outlier_detection/__init__.py
psod/outlier_detection/psod.py
psod/preprocessing/__init__.py
psod/preprocessing/full_preprocessing.py
psod/preprocessing/reduce_memory_footprint.py
psod/preprocessing/scale.py
psod/test.py
psod-1.3.0.dist-info/METADATA
psod-1.3.0.dist-info/WHEEL
psod-1.3.0.dist-info/RECORD
