Metadata-Version: 2.1
Name: psod
Version: 1.3.0
Summary: Outlier detection using supervised methods in an unsupervised context
Home-page: https://github.com/ThomasMeissnerDS/PSOD
License: GPL-3.0-only
Author: Thomas Meißner
Author-email: meissnercorporation@gmx.de
Requires-Python: >=3.7,<=3.11
Classifier: License :: OSI Approved :: GNU General Public License v3 (GPLv3)
Classifier: Programming Language :: Python :: 3
Classifier: Programming Language :: Python :: 3.7
Classifier: Programming Language :: Python :: 3.8
Classifier: Programming Language :: Python :: 3.9
Classifier: Programming Language :: Python :: 3.10
Classifier: Programming Language :: Python :: 3.11
Classifier: Programming Language :: Python :: 3.10
Classifier: Programming Language :: Python :: 3.7
Classifier: Programming Language :: Python :: 3.8
Classifier: Programming Language :: Python :: 3.9
Requires-Dist: category_encoders (>=2.3.0)
Requires-Dist: numpy (>=1.19.4)
Requires-Dist: pandas (>=1.1.5)
Requires-Dist: scikit-learn (>=1.0.1)
Requires-Dist: tqdm (>=4.00.0)
Project-URL: Repository, https://github.com/ThomasMeissnerDS/PSOD
